src/__init__.py
src/flake8_ast_error.py
src/flake8_pbp.py
src/checks/PBP101_range_len.py
src/checks/PBP102_json_dot_loads.py
src/checks/PBP103_open_no_with.py
src/checks/PBP104_requests_json_dumps.py
src/checks/PBP105_assigns_to_list.py
src/checks/PBP106_camel_case_func.py
src/checks/PBP107_default_mutable_args.py
src/checks/PBP108_compares_types.py
src/checks/PBP109_compares_to_true.py
src/checks/PBP110_inherits_from_object.py
src/checks/PBP111_not_using_ternary.py
src/checks/PBP112_using_filter.py
src/checks/PBP113_shadow_builtins.py
src/checks/PBP114_no_pointless_ternary.py
src/checks/PBP115_better_any.py
src/checks/__init__.py
flake8_pgp-1.1.16.dist-info/METADATA
flake8_pgp-1.1.16.dist-info/WHEEL
flake8_pgp-1.1.16.dist-info/entry_points.txt
flake8_pgp-1.1.16.dist-info/top_level.txt
flake8_pgp-1.1.16.dist-info/RECORD
